maxosc/__init__.py
maxosc/caller.py
maxosc/exceptions.py
maxosc/maxformatter.py
maxosc/maxosc.py
maxosc/oscloghandler.py
maxosc/parser.py
maxosc/sender.py
maxosc-0.0.6.dist-info/METADATA
maxosc-0.0.6.dist-info/WHEEL
maxosc-0.0.6.dist-info/top_level.txt
maxosc-0.0.6.dist-info/RECORD
