Metadata-Version: 2.1
Name: maxosc
Version: 0.0.6
Summary: Call python code from MaxMSP over OSC
Home-page: https://github.com/jobor019/pyosc
Author: Joakim Borg
Author-email: joakim.borg@ircam.fr
License: MIT
Platform: UNKNOWN
Requires-Dist: python-osc
